AUTHORS.rst
CONTRIBUTING.rst
HISTORY.rst
LICENSE
MANIFEST.in
README.rst
setup.cfg
setup.py
docs/Makefile
docs/authors.rst
docs/conf.py
docs/contributing.rst
docs/history.rst
docs/index.rst
docs/installation.rst
docs/make.bat
docs/readme.rst
docs/usage.rst
ghubtrending/__init__.py
ghubtrending/ghubtrending.py
ghubtrending.egg-info/PKG-INFO
ghubtrending.egg-info/SOURCES.txt
ghubtrending.egg-info/dependency_links.txt
ghubtrending.egg-info/entry_points.txt
ghubtrending.egg-info/not-zip-safe
ghubtrending.egg-info/requires.txt
ghubtrending.egg-info/top_level.txt
tests/__init__.py
tests/test_ghubtrending.py