Metadata-Version: 1.1
Name: ghubtrending
Version: 0.0.5
Summary: 
Home-page: https://github.com/XayOn/ghubtrending
Author: David Francos
Author-email: me@davidfrancos.net
License: BSD
Keywords: ghubtrending
Platform: UNKNOWN
Classifier: Development Status :: 2 - Pre-Alpha
Classifier: Intended Audience :: Developers
Classifier: License :: OSI Approved :: BSD License
Classifier: Natural Language :: English
Classifier: Programming Language :: Python :: 3
Classifier: Programming Language :: Python :: 3.3
Classifier: Programming Language :: Python :: 3.4
